README.md
setup.py
BaseballSimulator/Batters.py
BaseballSimulator/Pitchers.py
BaseballSimulator/Plotter.py
BaseballSimulator/Simulator.py
BaseballSimulator/__init__.py
BaseballSimulator/pdict.py
BaseballSimulator.egg-info/PKG-INFO
BaseballSimulator.egg-info/SOURCES.txt
BaseballSimulator.egg-info/dependency_links.txt
BaseballSimulator.egg-info/requires.txt
BaseballSimulator.egg-info/top_level.txt