Metadata-Version: 1.0
Name: BaseballSimulator
Version: 0.1.2
Summary: A module simulating the flight of a basebal, including deflection caused by spin.
Home-page: https://github.com/CD3/BaseballSimulator
Author: UNKNOWN
Author-email: UNKNOWN
License: UNKNOWN
Platform: UNKNOWN
